{
    "PJ016": {
        "pub_url": "https://pubmed.ncbi.nlm.nih.gov/30041684/",
        "pub_name": "Yuan et al. (2018)",
        "sex": "female",
        "cancer_type": "glioblastoma",
        "cancer_type_abbrev": "GBM",
        "grade": "4",
        "stage": "NA",
        "genomic_alteration": "IDH1 R132"
    },
    "PJ017": {
        "pub_url": "https://pubmed.ncbi.nlm.nih.gov/30041684/",
        "pub_name": "Yuan et al. (2018)",
        "sex": "male",
        "cancer_type": "glioblastoma",
        "cancer_type_abbrev": "GBM",
        "grade": "4",
        "stage": "NA",
        "genomic_alteration": "IDH1 wild-type"
    },
    "PJ018": {
        "pub_url": "https://pubmed.ncbi.nlm.nih.gov/30041684/",
        "pub_name": "Yuan et al. (2018)",
        "sex": "male",
        "cancer_type": "glioblastoma",
        "cancer_type_abbrev": "GBM",
        "grade": "4",
        "stage": "NA",
        "genomic_alteration": "IDH1 wild-type"
    },
    "PJ025": {
        "pub_url": "https://pubmed.ncbi.nlm.nih.gov/30041684/",
        "pub_name": "Yuan et al. (2018)",
        "sex": "male",
        "cancer_type": "glioblastoma",
        "cancer_type_abbrev": "GBM",
        "grade": "4",
        "stage": "NA",
        "genomic_alteration": "IDH1 wild-type"
    },
    "PJ030": {
        "pub_url": "https://pubmed.ncbi.nlm.nih.gov/30041684/",
        "pub_name": "Yuan et al. (2018)",
        "sex": "female",
        "cancer_type": "anaplastic astrocytoma",
        "cancer_type_abbrev": "LGG",
        "grade": "3",
        "stage": "NA",
        "genomic_alteration": "IDH1 wild-type"
    },
    "PJ032": {
        "pub_url": "https://pubmed.ncbi.nlm.nih.gov/30041684/",
        "pub_name": "Yuan et al. (2018)",
        "sex": "female",
        "cancer_type": "glioblastoma",
        "cancer_type_abbrev": "GBM",
        "grade": "unknown",
        "stage": "NA",
        "genomic_alteration": "IDH1 wild-type"
    },
    "PJ035": {
        "pub_url": "https://pubmed.ncbi.nlm.nih.gov/30041684/",
        "pub_name": "Yuan et al. (2018)",
        "sex": "male",
        "cancer_type": "glioblastoma",
        "cancer_type_abbrev": "GBM",
        "grade": "unknown",
        "stage": "NA",
        "genomic_alteration": "IDH1 wild-type"
    },
    "PJ048": {
        "pub_url": "https://pubmed.ncbi.nlm.nih.gov/30041684/",
        "pub_name": "Yuan et al. (2018)",
        "sex": "male",
        "cancer_type": "glioblastoma",
        "cancer_type_abbrev": "GBM",
        "grade": "4",
        "stage": "NA",
        "genomic_alteration": "IDH1 wild-type"
    },
    "LX653": {
        "pub_url": "https://pubmed.ncbi.nlm.nih.gov/32042191/",
        "pub_name": "Laughney et al. (2020)",
        "sex": "unknown",
        "cancer_type": "lung adenocarcinoma",
        "cancer_type_abbrev": "LUAD",
        "grade": "unknown",
        "stage": "1A",
        "genomic_alteration": "EGFR, KMT2D, U2AF1, RET"    
    },
    "LX661": {
        "pub_url": "https://pubmed.ncbi.nlm.nih.gov/32042191/",
        "pub_name": "Laughney et al. (2020)",
        "sex": "unknown", 
        "cancer_type": "lung adenocarcinoma",
        "cancer_type_abbrev": "LUAD",
        "grade": "unknown",
        "stage": "1A",
        "genomic_alteration": "EGFR, TP53"
    },
    "LX675": {
        "pub_url": "https://pubmed.ncbi.nlm.nih.gov/32042191/",
        "pub_name": "Laughney et al. (2020)",
        "sex": "unknown", 
        "cancer_type": "lung adenocarcinoma",
        "cancer_type_abbrev": "LUAD",
        "grade": "unknown",
        "stage": "4",
        "genomic_alteration": "EGFR"
    },
    "LX676": {
        "pub_url": "https://pubmed.ncbi.nlm.nih.gov/32042191/",
        "pub_name": "Laughney et al. (2020)",
        "sex": "unknown", 
        "cancer_type": "lung adenocarcinoma",
        "cancer_type_abbrev": "LUAD",
        "grade": "unknown",
        "stage": "1A",
        "genomic_alteration": "unknown"
    },
    "LX679": {
        "pub_url": "https://pubmed.ncbi.nlm.nih.gov/32042191/",
        "pub_name": "Laughney et al. (2020)",
        "sex": "unknown", 
        "cancer_type": "lung adenocarcinoma",
        "cancer_type_abbrev": "LUAD",
        "grade": "unknown",
        "stage": "2A",
        "genomic_alteration": "KRAS"
    },
    "LX680": {
        "pub_url": "https://pubmed.ncbi.nlm.nih.gov/32042191/",
        "pub_name": "Laughney et al. (2020)",
        "sex": "unknown", 
        "cancer_type": "lung adenocarcinoma",
        "cancer_type_abbrev": "LUAD",
        "grade": "unknown",
        "stage": "1B",
        "genomic_alteration": "TP53"
    },
    "LX682": {
        "pub_url": "https://pubmed.ncbi.nlm.nih.gov/32042191/",
        "pub_name": "Laughney et al. (2020)",
        "sex": "unknown", 
        "cancer_type": "lung adenocarcinoma",
        "cancer_type_abbrev": "LUAD",
        "grade": "unknown",
        "stage": "1B",
        "genomic_alteration": "KRAS"
    },
    "LX684": {
        "pub_url": "https://pubmed.ncbi.nlm.nih.gov/32042191/",
        "pub_name": "Laughney et al. (2020)",
        "sex": "unknown",
        "cancer_type": "lung adenocarcinoma",
        "cancer_type_abbrev": "LUAD",
        "grade": "unknown",
        "stage": "1A",
        "genomic_alteration": "KRAS"
    },
    "LX684": {
        "pub_url": "https://pubmed.ncbi.nlm.nih.gov/32042191/",
        "pub_name": "Laughney et al. (2020)",
        "sex": "unknown",
        "cancer_type": "lung adenocarcinoma",
        "cancer_type_abbrev": "LUAD",
        "grade": "unknown",
        "stage": "1A",
        "genomic_alteration": "KRAS"
    },
    "GSE146026.1": {
        "pub_url": "https://pubmed.ncbi.nlm.nih.gov/32572264/",
        "pub_name": "Izar et al. (2020)",
        "sex": "female",
        "cancer_type": "serous ovarian cancer",
        "cancer_type_abbrev": "OV",
        "grade": "high",
        "stage": "unknown",
        "genomic_alteration": "BRCA wild-type"
    },
    "GSE146026.2": {
        "pub_url": "https://pubmed.ncbi.nlm.nih.gov/32572264/",
        "pub_name": "Izar et al. (2020)",
        "sex": "female",
        "cancer_type": "serous ovarian cancer",
        "cancer_type_abbrev": "OV",
        "grade": "high",
        "stage": "unknown",
        "genomic_alteration": "BRCA wild-type"
    },
    "GSE146026.3": {
        "pub_url": "https://pubmed.ncbi.nlm.nih.gov/32572264/",
        "pub_name": "Izar et al. (2020)",
        "sex": "female",
        "cancer_type": "serous ovarian cancer",
        "cancer_type_abbrev": "OV",
        "grade": "high",
        "stage": "unknown",
        "genomic_alteration": "unknown"
    },
    "GSE146026.4": {
        "pub_url": "https://pubmed.ncbi.nlm.nih.gov/32572264/",
        "pub_name": "Izar et al. (2020)",
        "sex": "female",
        "cancer_type": "serous ovarian cancer",
        "cancer_type_abbrev": "OV",
        "grade": "high",
        "stage": "unknown",
        "genomic_alteration": "BRCA wild-type"
    },
    "GSE146026.5": {
        "pub_url": "https://pubmed.ncbi.nlm.nih.gov/32572264/",
        "pub_name": "Izar et al. (2020)",
        "sex": "female",
        "cancer_type": "serous ovarian cancer",
        "cancer_type_abbrev": "OV",
        "grade": "high",
        "stage": "unknown",
        "genomic_alteration": "BRCA wild-type"
    },
    "GSE146026.6": {
        "pub_url": "https://pubmed.ncbi.nlm.nih.gov/32572264/",
        "pub_name": "Izar et al. (2020)",
        "sex": "female",
        "cancer_type": "serous ovarian cancer",
        "cancer_type_abbrev": "OV",
        "grade": "high",
        "stage": "unknown",
        "genomic_alteration": "unknown"
    },
    "GSE72056.53": {
        "pub_url": "https://pubmed.ncbi.nlm.nih.gov/27124452/",
        "pub_name": "Tirosh et al. (2016)",
        "age": "77",
        "sex": "female",
        "cancer_type": "melanoma",
        "cancer_type_abbrev": "SKCM",
        "grade": "uknown",
        "stage": "unknown",
        "genomic_alteration": "BRAF wild-type, NRAS wild-type"
    },
    "GSE72056.58": {
        "pub_url": "https://pubmed.ncbi.nlm.nih.gov/27124452/",
        "pub_name": "Tirosh et al. (2016)",
        "age": "67",
        "sex": "female",
        "cancer_type": "melanoma",
        "cancer_type_abbrev": "SKCM",
        "grade": "uknown",
        "stage": "unknown",
        "genomic_alteration": "BRAF wild-type, NRAS wild-type"
    },
    "GSE72056.59": {
        "pub_url": "https://pubmed.ncbi.nlm.nih.gov/27124452/",
        "pub_name": "Tirosh et al. (2016)",
        "age": "80",
        "sex": "male",
        "cancer_type": "melanoma",
        "cancer_type_abbrev": "SKCM",
        "grade": "uknown",
        "stage": "unknown",
        "genomic_alteration": "BRAF wild-type, NRAS wild-type"
    },
    "GSE72056.60": {
        "pub_url": "https://pubmed.ncbi.nlm.nih.gov/27124452/",
        "pub_name": "Tirosh et al. (2016)",
        "age": "69",
        "sex": "male",
        "cancer_type": "melanoma",
        "cancer_type_abbrev": "SKCM",
        "grade": "uknown",
        "stage": "unknown",
        "genomic_alteration": "BRAF V600K, NRAS wild-type"
    },
    "GSE72056.65": {
        "pub_url": "https://pubmed.ncbi.nlm.nih.gov/27124452/",
        "pub_name": "Tirosh et al. (2016)",
        "age": "65",
        "sex": "male",
        "cancer_type": "melanoma",
        "cancer_type_abbrev": "SKCM",
        "grade": "uknown",
        "stage": "unknown",
        "genomic_alteration": "BRAF V600E, NRAS wild-type"
    },
    "GSE72056.67": {
        "pub_url": "https://pubmed.ncbi.nlm.nih.gov/27124452/",
        "pub_name": "Tirosh et al. (2016)",
        "age": "58",
        "sex": "male",
        "cancer_type": "melanoma",
        "cancer_type_abbrev": "SKCM",
        "grade": "uknown",
        "stage": "unknown",
        "genomic_alteration": "BRAF V600E, NRAS wild-type"
    },
    "GSE72056.71": {
        "pub_url": "https://pubmed.ncbi.nlm.nih.gov/27124452/",
        "pub_name": "Tirosh et al. (2016)",
        "age": "79",
        "sex": "male",
        "cancer_type": "melanoma",
        "cancer_type_abbrev": "SKCM",
        "grade": "uknown",
        "stage": "unknown",
        "genomic_alteration": "BRAF wild-type, NRAS Q61L"
    },
    "GSE72056.72": {
        "pub_url": "https://pubmed.ncbi.nlm.nih.gov/27124452/",
        "pub_name": "Tirosh et al. (2016)",
        "age": "57",
        "sex": "female",
        "cancer_type": "melanoma",
        "cancer_type_abbrev": "SKCM",
        "grade": "uknown",
        "stage": "unknown",
        "genomic_alteration": "BRAF wild-type, NRAS Q61R"
    },
    "GSE72056.74": {
        "pub_url": "https://pubmed.ncbi.nlm.nih.gov/27124452/",
        "pub_name": "Tirosh et al. (2016)",
        "age": "63",
        "sex": "male",
        "cancer_type": "melanoma",
        "cancer_type_abbrev": "SKCM",
        "grade": "uknown",
        "stage": "unknown",
        "genomic_alteration": "unknown"
    },
    "GSE72056.75": {
        "pub_url": "https://pubmed.ncbi.nlm.nih.gov/27124452/",
        "pub_name": "Tirosh et al. (2016)",
        "age": "80",
        "sex": "male",
        "cancer_type": "melanoma",
        "cancer_type_abbrev": "SKCM",
        "grade": "uknown",
        "stage": "unknown",
        "genomic_alteration": "BRAF wild-type, NRAS wild-type"
    },
    "GSE72056.78": {
        "pub_url": "https://pubmed.ncbi.nlm.nih.gov/27124452/",
        "pub_name": "Tirosh et al. (2016)",
        "age": "73",
        "sex": "male",
        "cancer_type": "melanoma",
        "cancer_type_abbrev": "SKCM",
        "grade": "uknown",
        "stage": "unknown",
        "genomic_alteration": "BRAF wild-type, NRAS Q61L"
    },
    "GSE72056.79": {
        "pub_url": "https://pubmed.ncbi.nlm.nih.gov/27124452/",
        "pub_name": "Tirosh et al. (2016)",
        "age": "74",
        "sex": "male",
        "cancer_type": "melanoma",
        "cancer_type_abbrev": "SKCM",
        "grade": "uknown",
        "stage": "unknown",
        "genomic_alteration": "BRAF wild-type, NRAS wild-type"
    },
    "GSE72056.80": {
        "pub_url": "https://pubmed.ncbi.nlm.nih.gov/27124452/",
        "pub_name": "Tirosh et al. (2016)",
        "age": "86",
        "sex": "female",
        "cancer_type": "melanoma",
        "cancer_type_abbrev": "SKCM",
        "grade": "uknown",
        "stage": "unknown",
        "genomic_alteration": "BRAF wild-type, NRAS Q61L"
    },
    "GSE72056.81": {
        "pub_url": "https://pubmed.ncbi.nlm.nih.gov/27124452/",
        "pub_name": "Tirosh et al. (2016)",
        "age": "43",
        "sex": "female",
        "cancer_type": "melanoma",
        "cancer_type_abbrev": "SKCM",
        "grade": "uknown",
        "stage": "unknown",
        "genomic_alteration": "BRAF V600E, NRAS wild-type"
    },
    "GSE72056.82": {
        "pub_url": "https://pubmed.ncbi.nlm.nih.gov/27124452/",
        "pub_name": "Tirosh et al. (2016)",
        "age": "81",
        "sex": "male",
        "cancer_type": "melanoma",
        "cancer_type_abbrev": "SKCM",
        "grade": "uknown",
        "stage": "unknown",
        "genomic_alteration": "BRAF wild-type, NRAS wild-type"
    },
    "GSE72056.84": {
        "pub_url": "https://pubmed.ncbi.nlm.nih.gov/27124452/",
        "pub_name": "Tirosh et al. (2016)",
        "age": "67",
        "sex": "male",
        "cancer_type": "melanoma",
        "cancer_type_abbrev": "SKCM",
        "grade": "uknown",
        "stage": "unknown",
        "genomic_alteration": "BRAF wild-type, NRAS wild-type"
    },
    "GSE72056.88": {
        "pub_url": "https://pubmed.ncbi.nlm.nih.gov/27124452/",
        "pub_name": "Tirosh et al. (2016)",
        "age": "54",
        "sex": "female",
        "cancer_type": "melanoma",
        "cancer_type_abbrev": "SKCM",
        "grade": "uknown",
        "stage": "unknown",
        "genomic_alteration": "BRAF wild-type, NRAS wild-type"
    },
    "GSE72056.89": {
        "pub_url": "https://pubmed.ncbi.nlm.nih.gov/27124452/",
        "pub_name": "Tirosh et al. (2016)",
        "age": "67",
        "sex": "male",
        "cancer_type": "melanoma",
        "cancer_type_abbrev": "SKCM",
        "grade": "uknown",
        "stage": "unknown",
        "genomic_alteration": "unknown"
    },
    "GSE72056.94": {
        "pub_url": "https://pubmed.ncbi.nlm.nih.gov/27124452/",
        "pub_name": "Tirosh et al. (2016)",
        "age": "54",
        "sex": "female",
        "cancer_type": "melanoma",
        "cancer_type_abbrev": "SKCM",
        "grade": "uknown",
        "stage": "unknown",
        "genomic_alteration": "BRAF wild-type, NRAS wild-type"
    },
    "GSE103322.5": {
        "pub_url": "https://pubmed.ncbi.nlm.nih.gov/29198524/",
        "pub_name": "Puram et al. (2017)",
        "age": "69",
        "sex": "female",
        "cancer_type": "head and neck squamous cell carcinoma",
        "cancer_type_abbrev": "HNSC",
        "grade": "2",
        "stage": "T2N1",
        "genomic_alteration": "TP53, TERT promoter, PIK3CA"
    },
    "GSE103322.6": {
        "pub_url": "https://pubmed.ncbi.nlm.nih.gov/29198524/",
        "pub_name": "Puram et al. (2017)",
        "age": "88",
        "sex": "female",
        "cancer_type": "head and neck squamous cell carcinoma",
        "cancer_type_abbrev": "HNSC",
        "grade": "1",
        "stage": "T4aN2c",
        "genomic_alteration": "TP53"
    },
    "GSE103322.7": {
        "pub_url": "https://pubmed.ncbi.nlm.nih.gov/29198524/",
        "pub_name": "Puram et al. (2017)",
        "age": "71",
        "sex": "female",
        "cancer_type": "head and neck squamous cell carcinoma",
        "cancer_type_abbrev": "HNSC",
        "grade": "3",
        "stage": "T1N2b",
        "genomic_alteration": "unknown"
    },
    "GSE103322.8": {
        "pub_url": "https://pubmed.ncbi.nlm.nih.gov/29198524/",
        "pub_name": "Puram et al. (2017)",
        "age": "82",
        "sex": "female",
        "cancer_type": "head and neck squamous cell carcinoma",
        "cancer_type_abbrev": "HNSC",
        "grade": "1",
        "stage": "T4aN0",
        "genomic_alteration": "unknown"
    },
    "GSE103322.9": {
        "pub_url": "https://pubmed.ncbi.nlm.nih.gov/29198524/",
        "pub_name": "Puram et al. (2017)",
        "age": "77",
        "sex": "female",
        "cancer_type": "head and neck squamous cell carcinoma",
        "cancer_type_abbrev": "HNSC",
        "grade": "2",
        "stage": "T1N0",
        "genomic_alteration": "unknown"
    },
    "GSE103322.10": {
        "pub_url": "https://pubmed.ncbi.nlm.nih.gov/29198524/",
        "pub_name": "Puram et al. (2017)",
        "age": "76",
        "sex": "male",
        "cancer_type": "head and neck squamous cell carcinoma",
        "cancer_type_abbrev": "HNSC",
        "grade": "2",
        "stage": "T4aN2b",
        "genomic_alteration": "unknown"
    },
    "GSE103322.12": {
        "pub_url": "https://pubmed.ncbi.nlm.nih.gov/29198524/",
        "pub_name": "Puram et al. (2017)",
        "age": "80",
        "sex": "male",
        "cancer_type": "head and neck squamous cell carcinoma",
        "cancer_type_abbrev": "HNSC",
        "grade": "2",
        "stage": "T4aN0",
        "genomic_alteration": "unknown"
    },
    "GSE103322.13": {
        "pub_url": "https://pubmed.ncbi.nlm.nih.gov/29198524/",
        "pub_name": "Puram et al. (2017)",
        "age": "52",
        "sex": "female",
        "cancer_type": "head and neck squamous cell carcinoma",
        "cancer_type_abbrev": "HNSC",
        "grade": "2",
        "stage": "T3N1",
        "genomic_alteration": "unknown"
    },
    "GSE103322.16": {
        "pub_url": "https://pubmed.ncbi.nlm.nih.gov/29198524/",
        "pub_name": "Puram et al. (2017)",
        "age": "63",
        "sex": "female",
        "cancer_type": "head and neck squamous cell carcinoma",
        "cancer_type_abbrev": "HNSC",
        "grade": "1",
        "stage": "T2N0",
        "genomic_alteration": "TERT promoter"
    },
    "GSE103322.17": {
        "pub_url": "https://pubmed.ncbi.nlm.nih.gov/29198524/",
        "pub_name": "Puram et al. (2017)",
        "age": "59",
        "sex": "male",
        "cancer_type": "head and neck squamous cell carcinoma",
        "cancer_type_abbrev": "HNSC",
        "grade": "2",
        "stage": "T4aN0",
        "genomic_alteration": "TERT promoter"
    },
    "GSE103322.18": {
        "pub_url": "https://pubmed.ncbi.nlm.nih.gov/29198524/",
        "pub_name": "Puram et al. (2017)",
        "age": "41",
        "sex": "male",
        "cancer_type": "head and neck squamous cell carcinoma",
        "cancer_type_abbrev": "HNSC",
        "grade": "2",
        "stage": "T3N1",
        "genomic_alteration": "TP53, PIK3CA"
    },
    "GSE103322.20": {
        "pub_url": "https://pubmed.ncbi.nlm.nih.gov/29198524/",
        "pub_name": "Puram et al. (2017)",
        "age": "53",
        "sex": "male",
        "cancer_type": "head and neck squamous cell carcinoma",
        "cancer_type_abbrev": "HNSC",
        "grade": "2",
        "stage": "T4aN2c",
        "genomic_alteration": "TP53, CDKN2A, NOTCH1"
    },
    "GSE103322.22": {
        "pub_url": "https://pubmed.ncbi.nlm.nih.gov/29198524/",
        "pub_name": "Puram et al. (2017)",
        "age": "77",
        "sex": "male",
        "cancer_type": "head and neck squamous cell carcinoma",
        "cancer_type_abbrev": "HNSC",
        "grade": "2",
        "stage": "T1N0",
        "genomic_alteration": "TP53, TERT promoter, CDKN2A"
    },
    "GSE103322.23": {
        "pub_url": "https://pubmed.ncbi.nlm.nih.gov/29198524/",
        "pub_name": "Puram et al. (2017)",
        "age": "56",
        "sex": "male",
        "cancer_type": "head and neck squamous cell carcinoma",
        "cancer_type_abbrev": "HNSC",
        "grade": "2",
        "stage": "T3N1",
        "genomic_alteration": "unknown"
    },
    "GSE103322.24": {
        "pub_url": "https://pubmed.ncbi.nlm.nih.gov/29198524/",
        "pub_name": "Puram et al. (2017)",
        "age": "78",
        "sex": "female",
        "cancer_type": "head and neck squamous cell carcinoma",
        "cancer_type_abbrev": "HNSC",
        "grade": "2",
        "stage": "T4aN2c",
        "genomic_alteration": "unknown"
    },
    "GSE103322.25": {
        "pub_url": "https://pubmed.ncbi.nlm.nih.gov/29198524/",
        "pub_name": "Puram et al. (2017)",
        "age": "76",
        "sex": "female",
        "cancer_type": "head and neck squamous cell carcinoma",
        "cancer_type_abbrev": "HNSC",
        "grade": "2",
        "stage": "T3N1",
        "genomic_alteration": "TP53, TERT promoter, FAT1, CDKN2A"
    },
    "GSE103322.26": {
        "pub_url": "https://pubmed.ncbi.nlm.nih.gov/29198524/",
        "pub_name": "Puram et al. (2017)",
        "age": "51",
        "sex": "male",
        "cancer_type": "head and neck squamous cell carcinoma",
        "cancer_type_abbrev": "HNSC",
        "grade": "3",
        "stage": "T4aN2c",
        "genomic_alteration": "TP53"
    },
    "GSE103322.28": {
        "pub_url": "https://pubmed.ncbi.nlm.nih.gov/29198524/",
        "pub_name": "Puram et al. (2017)",
        "age": "58",
        "sex": "male",
        "cancer_type": "head and neck squamous cell carcinoma",
        "cancer_type_abbrev": "HNSC",
        "grade": "1",
        "stage": "T2N2c",
        "genomic_alteration": "TERT promoter, NOTCH1"
    },
    "GSE111672.A": {
        "pub_url": "https://pubmed.ncbi.nlm.nih.gov/29198524/",
        "pub_name": "Moncada et al. (2020)",
        "age": "unknown",
        "sex": "unknown",
        "cancer_type": "pancreatic ductal adenocarcinoma",
        "cancer_type_abbrev": "PAAD",
        "grade": "unknown",
        "stage": "unknown",
        "genomic_alteration": "unknown"
    },
    "GSE111672.B": {
        "pub_url": "https://pubmed.ncbi.nlm.nih.gov/29198524/",
        "pub_name": "Moncada et al. (2020)",
        "age": "unknown",
        "sex": "unknown",
        "cancer_type": "pancreatic ductal adenocarcinoma",
        "cancer_type_abbrev": "PAAD",
        "grade": "unknown",
        "stage": "unknown",
        "genomic_alteration": "unknown"
    },
    "GSE118389.PT089": {
        "pub_url": "https://pubmed.ncbi.nlm.nih.gov/30181541/",
        "pub_name": "Karaayvaz et al. (2018)",
        "age": "44",
        "sex": "female",
        "cancer_type": "triple-negative breast invasive carcinoma",
        "cancer_type_abbrev": "BRCA",
        "grade": "2",
        "stage": "unknown",
        "genomic_alteration": "BRCA-"   
    }, 
    "GSE118389.PT039": {
        "pub_url": "https://pubmed.ncbi.nlm.nih.gov/30181541/",
        "pub_name": "Karaayvaz et al. (2018)",
        "age": "64",
        "sex": "female",
        "cancer_type": "triple-negative breast invasive carcinoma",
        "cancer_type_abbrev": "BRCA",
        "grade": "3",
        "stage": "unknown",
        "genomic_alteration": "BRCA-"       
    }, 
    "GSE118389.PT058": {
        "pub_url": "https://pubmed.ncbi.nlm.nih.gov/30181541/",
        "pub_name": "Karaayvaz et al. (2018)",
        "age": "46",
        "sex": "female",
        "cancer_type": "triple-negative breast invasive carcinoma",
        "cancer_type_abbrev": "BRCA",
        "grade": "3",
        "stage": "unknown",
        "genomic_alteration": "unknown"       
    }, 
    "GSE118389.PT081": {
        "pub_url": "https://pubmed.ncbi.nlm.nih.gov/30181541/",
        "pub_name": "Karaayvaz et al. (2018)",
        "age": "45",
        "sex": "female",
        "cancer_type": "triple-negative breast invasive carcinoma",
        "cancer_type_abbrev": "BRCA",
        "grade": "3",
        "stage": "unknown",
        "genomic_alteration": "BRCA-"       
    }, 
    "GSE118389.PT084": {
        "pub_url": "https://pubmed.ncbi.nlm.nih.gov/30181541/",
        "pub_name": "Karaayvaz et al. (2018)",
        "age": "52",
        "sex": "female",
        "cancer_type": "triple-negative breast invasive carcinoma",
        "cancer_type_abbrev": "BRCA",
        "grade": "3",
        "stage": "unknown",
        "genomic_alteration": "BRCA2+" 
    }, 
    "GSE118389.PT126": {
        "pub_url": "https://pubmed.ncbi.nlm.nih.gov/30181541/",
        "pub_name": "Karaayvaz et al. (2018)",
        "age": "42",
        "sex": "female",
        "cancer_type": "triple-negative breast invasive carcinoma",
        "cancer_type_abbrev": "BRCA",
        "grade": "3",
        "stage": "unknown",
        "genomic_alteration": "BRCA2 VUS"       
    },
    "GSE123814.su001.pre_treatment": {
        "pub_url": "https://pubmed.ncbi.nlm.nih.gov/31359002/",
        "pub_name": "Yost et al. (2019)",
        "age": "",
        "sex": "",
        "cancer_type": "basal cell carcinoma",
        "cancer_type_abbrev": "BCC",
        "grade": "",
        "stage": "",
        "genomic_alteration": ""
    }, 
    "GSE123814.su002.pre_treatment": {
        "pub_url": "https://pubmed.ncbi.nlm.nih.gov/31359002/",
        "pub_name": "Yost et al. (2019)",
        "age": "",
        "sex": "",
        "cancer_type": "basal cell carcinoma",
        "cancer_type_abbrev": "BCC",
        "grade": "",
        "stage": "",
        "genomic_alteration": ""
    },
    "GSE123814.su003.pre_treatment": {
        "pub_url": "https://pubmed.ncbi.nlm.nih.gov/31359002/",
        "pub_name": "Yost et al. (2019)",
        "age": "",
        "sex": "",
        "cancer_type": "basal cell carcinoma",
        "cancer_type_abbrev": "BCC",
        "grade": "",
        "stage": "",
        "genomic_alteration": ""
    },
    "GSE123814.su004.pre_treatment": {
        "pub_url": "https://pubmed.ncbi.nlm.nih.gov/31359002/",
        "pub_name": "Yost et al. (2019)",
        "age": "",
        "sex": "",
        "cancer_type": "basal cell carcinoma",
        "cancer_type_abbrev": "BCC",
        "grade": "",
        "stage": "",
        "genomic_alteration": ""
    },
    "GSE123814.su005.pre_treatment": {
        "pub_url": "https://pubmed.ncbi.nlm.nih.gov/31359002/",
        "pub_name": "Yost et al. (2019)",
        "age": "",
        "sex": "",
        "cancer_type": "basal cell carcinoma",
        "cancer_type_abbrev": "BCC",
        "grade": "",
        "stage": "",
        "genomic_alteration": ""
    },
    "GSE123814.su006.pre_treatment": {
        "pub_url": "https://pubmed.ncbi.nlm.nih.gov/31359002/",
        "pub_name": "Yost et al. (2019)",
        "age": "",
        "sex": "",
        "cancer_type": "basal cell carcinoma",
        "cancer_type_abbrev": "BCC",
        "grade": "",
        "stage": "",
        "genomic_alteration": ""
    },
    "GSE123814.su007.pre_treatment": {
        "pub_url": "https://pubmed.ncbi.nlm.nih.gov/31359002/",
        "pub_name": "Yost et al. (2019)",
        "age": "",
        "sex": "",
        "cancer_type": "basal cell carcinoma",
        "cancer_type_abbrev": "BCC",
        "grade": "",
        "stage": "",
        "genomic_alteration": ""
    },
    "GSE123814.su008.pre_treatment": {
        "pub_url": "https://pubmed.ncbi.nlm.nih.gov/31359002/",
        "pub_name": "Yost et al. (2019)",
        "age": "",
        "sex": "",
        "cancer_type": "basal cell carcinoma",
        "cancer_type_abbrev": "BCC",
        "grade": "",
        "stage": "",
        "genomic_alteration": ""
    },
    "GSE123814.su009.pre_treatment": {
        "pub_url": "https://pubmed.ncbi.nlm.nih.gov/31359002/",
        "pub_name": "Yost et al. (2019)",
        "age": "",
        "sex": "",
        "cancer_type": "basal cell carcinoma",
        "cancer_type_abbrev": "BCC",
        "grade": "",
        "stage": "",
        "genomic_alteration": ""
    },
    "GSE123814.su010.pre_treatment": {
        "pub_url": "https://pubmed.ncbi.nlm.nih.gov/31359002/",
        "pub_name": "Yost et al. (2019)",
        "age": "",
        "sex": "",
        "cancer_type": "basal cell carcinoma",
        "cancer_type_abbrev": "BCC",
        "grade": "",
        "stage": "",
        "genomic_alteration": ""
    },
    "GSE123814.su012.pre_treatment": {
        "pub_url": "https://pubmed.ncbi.nlm.nih.gov/31359002/",
        "pub_name": "Yost et al. (2019)",
        "age": "",
        "sex": "",
        "cancer_type": "basal cell carcinoma",
        "cancer_type_abbrev": "BCC",
        "grade": "",
        "stage": "",
        "genomic_alteration": ""
    },
    "GSE123814.su001.post_treatment": {
        "pub_url": "https://pubmed.ncbi.nlm.nih.gov/31359002/",
        "pub_name": "Yost et al. (2019)",
        "age": "",
        "sex": "",
        "cancer_type": "basal cell carcinoma",
        "cancer_type_abbrev": "BCC",
        "grade": "",
        "stage": "",
        "genomic_alteration": ""
    }, 
    "GSE123814.su002.post_treatment": {
        "pub_url": "https://pubmed.ncbi.nlm.nih.gov/31359002/",
        "pub_name": "Yost et al. (2019)",
        "age": "",
        "sex": "",
        "cancer_type": "basal cell carcinoma",
        "cancer_type_abbrev": "BCC",
        "grade": "",
        "stage": "",
        "genomic_alteration": ""
    }, 
    "GSE123814.su003.post_treatment": {
        "pub_url": "https://pubmed.ncbi.nlm.nih.gov/31359002/",
        "pub_name": "Yost et al. (2019)",
        "age": "",
        "sex": "",
        "cancer_type": "basal cell carcinoma",
        "cancer_type_abbrev": "BCC",
        "grade": "",
        "stage": "",
        "genomic_alteration": ""
    },
    "GSE123814.su004.post_treatment": {
        "pub_url": "https://pubmed.ncbi.nlm.nih.gov/31359002/",
        "pub_name": "Yost et al. (2019)",
        "age": "",
        "sex": "",
        "cancer_type": "basal cell carcinoma",
        "cancer_type_abbrev": "BCC",
        "grade": "",
        "stage": "",
        "genomic_alteration": ""
    },
    "GSE123814.su005.post_treatment": {
        "pub_url": "https://pubmed.ncbi.nlm.nih.gov/31359002/",
        "pub_name": "Yost et al. (2019)",
        "age": "",
        "sex": "",
        "cancer_type": "basal cell carcinoma",
        "cancer_type_abbrev": "BCC",
        "grade": "",
        "stage": "",
        "genomic_alteration": ""
    },
    "GSE123814.su006.post_treatment": {
        "pub_url": "https://pubmed.ncbi.nlm.nih.gov/31359002/",
        "pub_name": "Yost et al. (2019)",
        "age": "",
        "sex": "",
        "cancer_type": "basal cell carcinoma",
        "cancer_type_abbrev": "BCC",
        "grade": "",
        "stage": "",
        "genomic_alteration": ""
    },
    "GSE123814.su007.post_treatment": {
        "pub_url": "https://pubmed.ncbi.nlm.nih.gov/31359002/",
        "pub_name": "Yost et al. (2019)",
        "age": "",
        "sex": "",
        "cancer_type": "basal cell carcinoma",
        "cancer_type_abbrev": "BCC",
        "grade": "",
        "stage": "",
        "genomic_alteration": ""
    },
    "GSE123814.su008.post_treatment": {
        "pub_url": "https://pubmed.ncbi.nlm.nih.gov/31359002/",
        "pub_name": "Yost et al. (2019)",
        "age": "",
        "sex": "",
        "cancer_type": "basal cell carcinoma",
        "cancer_type_abbrev": "BCC",
        "grade": "",
        "stage": "",
        "genomic_alteration": ""
    },
    "GSE123814.su009.post_treatment": {
        "pub_url": "https://pubmed.ncbi.nlm.nih.gov/31359002/",
        "pub_name": "Yost et al. (2019)",
        "age": "",
        "sex": "",
        "cancer_type": "basal cell carcinoma",
        "cancer_type_abbrev": "BCC",
        "grade": "",
        "stage": "",
        "genomic_alteration": ""
    },
    "GSE123814.su010.post_treatment": {
        "pub_url": "https://pubmed.ncbi.nlm.nih.gov/31359002/",
        "pub_name": "Yost et al. (2019)",
        "age": "",
        "sex": "",
        "cancer_type": "basal cell carcinoma",
        "cancer_type_abbrev": "BCC",
        "grade": "",
        "stage": "",
        "genomic_alteration": ""
    },
    "GSE123814.su012.post_treatment": {
        "pub_url": "https://pubmed.ncbi.nlm.nih.gov/31359002/",
        "pub_name": "Yost et al. (2019)",
        "age": "",
        "sex": "",
        "cancer_type": "basal cell carcinoma",
        "cancer_type_abbrev": "BCC",
        "grade": "",
        "stage": "",
        "genomic_alteration": ""
    },
    "GSE115978.Mel194": {
        "pub_url": "https://pubmed.ncbi.nlm.nih.gov/30388455/",
        "pub_name": "Jerby-Arnon et al. (2018)",
        "age": "68",
        "sex": "male",
        "cancer_type": "melanoma",
        "cancer_type_abbrev": "SKCM",
        "grade": "unknown",
        "stage": "unknown",
        "genomic_alteration": "unknown",
        "lesion_type": "metastasis"
    },
    "GSE115978.Mel102": {
        "pub_url": "https://pubmed.ncbi.nlm.nih.gov/30388455/",
        "pub_name": "Jerby-Arnon et al. (2018)",
        "age": "72",
        "sex": "female",
        "cancer_type": "melanoma",
        "cancer_type_abbrev": "SKCM",
        "grade": "unknown",
        "stage": "unknown",
        "genomic_alteration": "unknown",
        "lesion_type": "metastasis"
    },
    "GSE115978.Mel112": {
        "pub_url": "https://pubmed.ncbi.nlm.nih.gov/30388455/",
        "pub_name": "Jerby-Arnon et al. (2018)",
        "age": "76",
        "sex": "male",
        "cancer_type": "melanoma",
        "cancer_type_abbrev": "SKCM",
        "grade": "unknown",
        "stage": "unknown",
        "genomic_alteration": "unknown",
        "lesion_type": "metastasis"
    },
    "GSE115978.Mel98": {
        "pub_url": "https://pubmed.ncbi.nlm.nih.gov/30388455/",
        "pub_name": "Jerby-Arnon et al. (2018)",
        "age": "47",
        "sex": "female",
        "cancer_type": "melanoma",
        "cancer_type_abbrev": "SKCM",
        "grade": "unknown",
        "stage": "unknown",
        "genomic_alteration": "unknown",
        "lesion_type": "metastasis"
    },
    "GSE115978.Mel110": {
        "pub_url": "https://pubmed.ncbi.nlm.nih.gov/30388455/",
        "pub_name": "Jerby-Arnon et al. (2018)",
        "age": "74",
        "sex": "male",
        "cancer_type": "melanoma",
        "cancer_type_abbrev": "SKCM",
        "grade": "unknown",
        "stage": "unknown",
        "genomic_alteration": "unknown",
        "lesion_type": "metastasis"
    },
    "GSE115978.Mel103": {
        "pub_url": "https://pubmed.ncbi.nlm.nih.gov/30388455/",
        "pub_name": "Jerby-Arnon et al. (2018)",
        "age": "58",
        "sex": "male",
        "cancer_type": "melanoma",
        "cancer_type_abbrev": "SKCM",
        "grade": "unknown",
        "stage": "unknown",
        "genomic_alteration": "unknown",
        "lesion_type": "metastasis"
    },
    "GSE115978.Mel75": {
        "pub_url": "https://pubmed.ncbi.nlm.nih.gov/30388455/",
        "pub_name": "Jerby-Arnon et al. (2018)",
        "age": "81",
        "sex": "male",
        "cancer_type": "melanoma",
        "cancer_type_abbrev": "SKCM",
        "grade": "unknown",
        "stage": "unknown",
        "genomic_alteration": "unknown",
        "lesion_type": "metastasis"
    },
    "GSE115978.Mel105": {
        "pub_url": "https://pubmed.ncbi.nlm.nih.gov/30388455/",
        "pub_name": "Jerby-Arnon et al. (2018)",
        "age": "77",
        "sex": "male",
        "cancer_type": "melanoma",
        "cancer_type_abbrev": "SKCM",
        "grade": "unknown",
        "stage": "unknown",
        "genomic_alteration": "uknown",
        "lesion_type": "primary"
    },
    "GSE115978.Mel106": {
        "pub_url": "https://pubmed.ncbi.nlm.nih.gov/30388455/",
        "pub_name": "Jerby-Arnon et al. (2018)",
        "age": "67",
        "sex": "male",
        "cancer_type": "melanoma",
        "cancer_type_abbrev": "SKCM",
        "grade": "unknown",
        "stage": "unknown",
        "genomic_alteration": "unknown",
        "lesion_type": "metastasis"
    },
    "GSE115978.Mel116": {
        "pub_url": "https://pubmed.ncbi.nlm.nih.gov/30388455/",
        "pub_name": "Jerby-Arnon et al. (2018)",
        "age": "85",
        "sex": "male",
        "cancer_type": "melanoma",
        "cancer_type_abbrev": "SKCM",
        "grade": "unknown",
        "stage": "unknown",
        "genomic_alteration": "unknown",
        "lesion_type": "metastasis"
    },
    "GSE115978.Mel478": {
        "pub_url": "https://pubmed.ncbi.nlm.nih.gov/30388455/",
        "pub_name": "Jerby-Arnon et al. (2018)",
        "age": "54",
        "sex": "female",
        "cancer_type": "melanoma",
        "cancer_type_abbrev": "SKCM",
        "grade": "unknown",
        "stage": "unknown",
        "genomic_alteration": "unknown",
        "lesion_type": "metastasis"
    },
    "GSE115978.Mel126": {
        "pub_url": "https://pubmed.ncbi.nlm.nih.gov/30388455/",
        "pub_name": "Jerby-Arnon et al. (2018)",
        "age": "63",
        "sex": "male",
        "cancer_type": "melanoma",
        "cancer_type_abbrev": "SKCM",
        "grade": "unknown",
        "stage": "unknown",
        "genomic_alteration": "unknown",
        "lesion_type": "metastasis"
    },
    "GSE115978.Mel129pa": {
        "pub_url": "https://pubmed.ncbi.nlm.nih.gov/30388455/",
        "pub_name": "Jerby-Arnon et al. (2018)",
        "age": "63",
        "sex": "male",
        "cancer_type": "melanoma",
        "cancer_type_abbrev": "SKCM",
        "grade": "unknown",
        "stage": "unknown",
        "genomic_alteration": "unknown",
        "lesion_type": "primary"
    },
    "GSE115978.Mel04.3": {
        "pub_url": "https://pubmed.ncbi.nlm.nih.gov/30388455/",
        "pub_name": "Jerby-Arnon et al. (2018)",
        "age": "81",
        "sex": "male",
        "cancer_type": "melanoma",
        "cancer_type_abbrev": "SKCM",
        "grade": "unknown",
        "stage": "unknown",
        "genomic_alteration": "unknown",
        "lesion_type": "metastasis"
    },
    "GSE115978.Mel121.1": {
        "pub_url": "https://pubmed.ncbi.nlm.nih.gov/30388455/",
        "pub_name": "Jerby-Arnon et al. (2018)",
        "age": "74",
        "sex": "male",
        "cancer_type": "melanoma",
        "cancer_type_abbrev": "SKCM",
        "grade": "unknown",
        "stage": "unknown",
        "genomic_alteration": "unknown",
        "lesion_type": "metastasis"
    },
    "GSE115978.Mel128": {
        "pub_url": "https://pubmed.ncbi.nlm.nih.gov/30388455/",
        "pub_name": "Jerby-Arnon et al. (2018)",
        "age": "37",
        "sex": "male",
        "cancer_type": "melanoma",
        "cancer_type_abbrev": "SKCM",
        "grade": "unknown",
        "stage": "unknown",
        "genomic_alteration": "unknown",
        "lesion_type": "metastasis"
    },
    "GSE117891.S1": {
        "pub_url": "https://doi.org/10.1093/nsr/nwaa099",
        "pub_name": "Yu et al. (2020)",
        "age": "34",
        "sex": "female",
        "cancer_type": "glioblastoma",
        "cancer_type_abbrev": "GBM",
        "grade": "4",
        "stage": "NA",
        "genomic_alteration": "MGMT promoter methylation",
        "lesion_type": "primary"
    },
    "GSE117891.S2": {
        "pub_url": "https://doi.org/10.1093/nsr/nwaa099",
        "pub_name": "Yu et al. (2020)",
        "age": "44",
        "sex": "male",
        "cancer_type": "glioblastoma",
        "cancer_type_abbrev": "GBM",
        "grade": "4",
        "stage": "NA",
        "genomic_alteration": "MGMT promoter methylation",
        "lesion_type": "primary"
    }, 
    "GSE117891.S3": {
        "pub_url": "https://doi.org/10.1093/nsr/nwaa099",
        "pub_name": "Yu et al. (2020)",
        "age": "66",
        "sex": "female",
        "cancer_type": "glioblastoma",
        "cancer_type_abbrev": "GBM",
        "grade": "4",
        "stage": "NA",
        "genomic_alteration": "TERT promoter C250T",
        "lesion_type": "primary"
    },
    "GSE117891.S4": {
        "pub_url": "https://doi.org/10.1093/nsr/nwaa099",
        "pub_name": "Yu et al. (2020)",
        "age": "65",
        "sex": "female",
        "cancer_type": "gliosarcoma",
        "cancer_type_abbrev": "GBM",
        "grade": "4",
        "stage": "NA",
        "genomic_alteration": "unknown",
        "lesion_type": "primary"
    },
    "GSE117891.S5": {
        "pub_url": "https://doi.org/10.1093/nsr/nwaa099",
        "pub_name": "Yu et al. (2020)",
        "age": "64",
        "sex": "female",
        "cancer_type": "glioblastoma",
        "cancer_type_abbrev": "GBM",
        "grade": "4",
        "stage": "NA",
        "genomic_alteration": "TERT promoter C228T",
        "lesion_type": "primary"
    },
    "GSE117891.S6": {
        "pub_url": "https://doi.org/10.1093/nsr/nwaa099",
        "pub_name": "Yu et al. (2020)",
        "age": "51",
        "sex": "male",
        "cancer_type": "glioblastoma",
        "cancer_type_abbrev": "GBM",
        "grade": "4",
        "stage": "NA",
        "genomic_alteration": "MGMT promoter methylation, TERT promoter C228T",
        "lesion_type": "primary"
    },
    "GSE117891.S7": {
        "pub_url": "https://doi.org/10.1093/nsr/nwaa099",
        "pub_name": "Yu et al. (2020)",
        "age": "male",
        "sex": "52",
        "cancer_type": "glioblastoma",
        "cancer_type_abbrev": "GBM",
        "grade": "3-4",
        "stage": "NA",
        "genomic_alteration": "IDH1 R132, TERT promoter C228T",
        "lesion_type": "primary"
    },
    "GSE117891.S8": {
        "pub_url": "https://doi.org/10.1093/nsr/nwaa099",
        "pub_name": "Yu et al. (2020)",
        "age": "29",
        "sex": "male",
        "cancer_type": "low-grade glioma",
        "cancer_type_abbrev": "LGG",
        "grade": "2",
        "stage": "NA",
        "genomic_alteration": "IDH1 R132, MGMT promoter methylation, TERT promoter C228T",
        "lesion_type": "primary"
    },
    "GSE117891.S9": {
        "pub_url": "https://doi.org/10.1093/nsr/nwaa099",
        "pub_name": "Yu et al. (2020)",
        "age": "44",
        "sex": "male",
        "cancer_type": "low-grade glioma",
        "cancer_type_abbrev": "LGG",
        "grade": "2",
        "stage": "NA",
        "genomic_alteration": "NA",
        "lesion_type": "primary"
    },
    "GSE117891.S11": {
        "pub_url": "https://doi.org/10.1093/nsr/nwaa099",
        "pub_name": "Yu et al. (2020)",
        "age": "48",
        "sex": "male",
        "cancer_type": "glioblastoma",
        "cancer_type_abbrev": "GBM",
        "grade": "4",
        "stage": "NA",
        "genomic_alteration": "unknown",
        "lesion_type": "primary"
    },
    "GSE117891.S12": {
        "pub_url": "https://doi.org/10.1093/nsr/nwaa099",
        "pub_name": "Yu et al. (2020)",
        "age": "64",
        "sex": "male",
        "cancer_type": "glioblastoma",
        "cancer_type_abbrev": "GBM",
        "grade": "4",
        "stage": "NA",
        "genomic_alteration": "unknown",
        "lesion_type": "primary"
    },
    "GSE117891.S13": {
        "pub_url": "https://doi.org/10.1093/nsr/nwaa099",
        "pub_name": "Yu et al. (2020)",
        "age": "52",
        "sex": "male",
        "cancer_type": "glioblastoma",
        "cancer_type_abbrev": "GBM",
        "grade": "4",
        "stage": "NA",
        "genomic_alteration": "MGMT promoter methylation, TERT promoter C250T",
        "lesion_type": "primary"
    },
    "GSE117891.S14": {
        "pub_url": "https://doi.org/10.1093/nsr/nwaa099",
        "pub_name": "Yu et al. (2020)",
        "age": "47",
        "sex": "female",
        "cancer_type": "low-grade glioma",
        "cancer_type_abbrev": "LGG",
        "grade": "2",
        "stage": "NA",
        "genomic_alteration": "IDH1 R132, MGMT promoter methylation, TERT promoter C250T",
        "lesion_type": "primary"
    },
    "GSE117891.S15": {
        "pub_url": "https://doi.org/10.1093/nsr/nwaa099",
        "pub_name": "Yu et al. (2020)",
        "age": "61",
        "sex": "male",
        "cancer_type": "lung squamous cell carcinoma",
        "cancer_type_abbrev": "LUSC",
        "grade": "unknown",
        "stage": "unknown",
        "genomic_alteration": "unknown",
        "lesion_type": "metastasis"
    },
    "GSE70630.MGH36": {
        "pub_url": "https://pubmed.ncbi.nlm.nih.gov/27806376/",
        "pub_name": "Tirosh et al. (2016)",
        "age": "67",
        "sex": "male",
        "cancer_type": "oligodendroglioma",
        "cancer_type_abbrev": "LGG",
        "grade": "2-3",
        "stage": "NA",
        "genomic_alteration": "R132H",
        "lesion_type": "primary"
    },
    "GSE70630.MGH53": {
        "pub_url": "https://pubmed.ncbi.nlm.nih.gov/27806376/",
        "pub_name": "Tirosh et al. (2016)",
        "age": "31",
        "sex": "male",
        "cancer_type": "oligodendroglioma",
        "cancer_type_abbrev": "LGG",
        "grade": "2",
        "stage": "NA",
        "genomic_alteration": "R132H",
        "lesion_type": "primary"
    },
    "GSE70630.MGH54": {
        "pub_url": "https://pubmed.ncbi.nlm.nih.gov/27806376/",
        "pub_name": "Tirosh et al. (2016)",
        "age": "35",
        "sex": "male",
        "cancer_type": "oligodendroglioma",
        "cancer_type_abbrev": "LGG",
        "grade": "2",
        "stage": "NA",
        "genomic_alteration": "R132H",
        "lesion_type": "primary"
    },
    "GSE70630.MGH60": {
        "pub_url": "https://pubmed.ncbi.nlm.nih.gov/27806376/",
        "pub_name": "Tirosh et al. (2016)",
        "age": "51",
        "sex": "male",
        "cancer_type": "oligodendroglioma",
        "cancer_type_abbrev": "LGG",
        "grade": "2",
        "stage": "NA",
        "genomic_alteration": "R132H",
        "lesion_type": "primary"
    },
    "GSE70630.MGH97": {
        "pub_url": "https://pubmed.ncbi.nlm.nih.gov/27806376/",
        "pub_name": "Tirosh et al. (2016)",
        "age": "31",
        "sex": "male",
        "cancer_type": "oligodendroglioma",
        "cancer_type_abbrev": "LGG",
        "grade": "2",
        "stage": "NA",
        "genomic_alteration": "R172K",
        "lesion_type": "primary"
    },
    "GSE70630.MGH93": {
        "pub_url": "https://pubmed.ncbi.nlm.nih.gov/27806376/",
        "pub_name": "Tirosh et al. (2016)",
        "age": "65",
        "sex": "female",
        "cancer_type": "oligodendroglioma",
        "cancer_type_abbrev": "LGG",
        "grade": "2",
        "stage": "NA",
        "genomic_alteration": "R132H",
        "lesion_type": "primary"
    },
    "GSE131928.MGH101": {
        "pub_url": "https://pubmed.ncbi.nlm.nih.gov/31327527/",
        "pub_name": "Neftel et al. (2019)",
        "age": "52",
        "sex": "male",
        "cancer_type": "glioblastoma",
        "cancer_type_abbrev": "GBM",
        "grade": "4",
        "stage": "NA",
        "genomic_alteration": "MGMT non-methylated",
        "lesion_type": "primary"
    },
    "GSE131928.MGH100": {
        "pub_url": "https://pubmed.ncbi.nlm.nih.gov/31327527/",
        "pub_name": "Neftel et al. (2019)",
        "age": "71",
        "sex": "female",
        "cancer_type": "glioblastoma",
        "cancer_type_abbrev": "GBM",
        "grade": "4",
        "stage": "NA",
        "genomic_alteration": "MGMT methylated",
        "lesion_type": "primary"
    },
    "GSE131928.MGH102": {
        "pub_url": "https://pubmed.ncbi.nlm.nih.gov/31327527/",
        "pub_name": "Neftel et al. (2019)",
        "age": "65",
        "sex": "male",
        "cancer_type": "glioblastoma",
        "cancer_type_abbrev": "GBM",
        "grade": "4",
        "stage": "NA",
        "genomic_alteration": "MGMT non-methylated",
        "lesion_type": "primary"
    },
    "GSE131928.MGH110": {
        "pub_url": "https://pubmed.ncbi.nlm.nih.gov/31327527/",
        "pub_name": "Neftel et al. (2019)",
        "age": "61",
        "sex": "male",
        "cancer_type": "glioblastoma",
        "cancer_type_abbrev": "GBM",
        "grade": "4",
        "stage": "NA",
        "genomic_alteration": "MGMT non-methylated",
        "lesion_type": "primary"
    },
    "GSE131928.MGH113": {
        "pub_url": "https://pubmed.ncbi.nlm.nih.gov/31327527/",
        "pub_name": "Neftel et al. (2019)",
        "age": "65",
        "sex": "male",
        "cancer_type": "glioblastoma",
        "cancer_type_abbrev": "GBM",
        "grade": "4",
        "stage": "NA",
        "genomic_alteration": "EGFR positive, MGMT non-methylated",
        "lesion_type": "primary"
    },
    "GSE131928.MGH115": {
        "pub_url": "https://pubmed.ncbi.nlm.nih.gov/31327527/",
        "pub_name": "Neftel et al. (2019)",
        "age": "69",
        "sex": "female",
        "cancer_type": "glioblastoma",
        "cancer_type_abbrev": "GBM",
        "grade": "4",
        "stage": "NA",
        "genomic_alteration": "EGFR positive, MGMT non-methylated",
        "lesion_type": "primary"
    },
    "GSE131928.MGH121": {
        "pub_url": "https://pubmed.ncbi.nlm.nih.gov/31327527/",
        "pub_name": "Neftel et al. (2019)",
        "age": "63",
        "sex": "male",
        "cancer_type": "glioblastoma",
        "cancer_type_abbrev": "GBM",
        "grade": "4",
        "stage": "NA",
        "genomic_alteration": "MGMT non-methylated",
        "lesion_type": "primary"
    },
    "GSE131928.MGH122": {
        "pub_url": "https://pubmed.ncbi.nlm.nih.gov/31327527/",
        "pub_name": "Neftel et al. (2019)",
        "age": "63",
        "sex": "male",
        "cancer_type": "glioblastoma",
        "cancer_type_abbrev": "GBM",
        "grade": "4",
        "stage": "NA",
        "genomic_alteration": "MGMT non-methylated",
        "lesion_type": "primary"
    },
    "GSE131928.MGH124": {
        "pub_url": "https://pubmed.ncbi.nlm.nih.gov/31327527/",
        "pub_name": "Neftel et al. (2019)",
        "age": "68",
        "sex": "female",
        "cancer_type": "glioblastoma",
        "cancer_type_abbrev": "GBM",
        "grade": "4",
        "stage": "NA",
        "genomic_alteration": "MGMT non-methylated",
        "lesion_type": "primary"
    },
    "GSE131928.MGH125": {
        "pub_url": "https://pubmed.ncbi.nlm.nih.gov/31327527/",
        "pub_name": "Neftel et al. (2019)",
        "age": "76",
        "sex": "male",
        "cancer_type": "glioblastoma",
        "cancer_type_abbrev": "GBM",
        "grade": "4",
        "stage": "NA",
        "genomic_alteration": "MGMT non-methylated",
        "lesion_type": "primary"
    },
    "GSE131928.MGHBT749": {
        "pub_url": "https://pubmed.ncbi.nlm.nih.gov/31327527/",
        "pub_name": "Neftel et al. (2019)",
        "age": "9 months",
        "sex": "female",
        "cancer_type": "glioblastoma",
        "cancer_type_abbrev": "GBM",
        "grade": "4",
        "stage": "NA",
        "genomic_alteration": "unknown",
        "lesion_type": "primary"
    },
    "GSE131928.MGHBT771": {
        "pub_url": "https://pubmed.ncbi.nlm.nih.gov/31327527/",
        "pub_name": "Neftel et al. (2019)",
        "age": "12",
        "sex": "female",
        "cancer_type": "glioblastoma",
        "cancer_type_abbrev": "GBM",
        "grade": "4",
        "stage": "NA",
        "genomic_alteration": "MGMT methylated",
        "lesion_type": "primary"
    },
    "GSE131928.MGHBT830": {
        "pub_url": "https://pubmed.ncbi.nlm.nih.gov/31327527/",
        "pub_name": "Neftel et al. (2019)",
        "age": "7",
        "sex": "female",
        "cancer_type": "glioblastoma",
        "cancer_type_abbrev": "GBM",
        "grade": "4",
        "stage": "NA",
        "genomic_alteration": "uknown",
        "lesion_type": "primary"
    },
    "GSE131928.MGH85": {
        "pub_url": "https://pubmed.ncbi.nlm.nih.gov/31327527/",
        "pub_name": "Neftel et al. (2019)",
        "age": "7",
        "sex": "female",
        "cancer_type": "glioblastoma",
        "cancer_type_abbrev": "GBM",
        "grade": "4",
        "stage": "NA",
        "genomic_alteration": "unknown",
        "lesion_type": "recurrence"
    },
    "GSE131928.MGHBT1160": {
        "pub_url": "https://pubmed.ncbi.nlm.nih.gov/31327527/",
        "pub_name": "Neftel et al. (2019)",
        "age": "11",
        "sex": "female",
        "cancer_type": "glioblastoma",
        "cancer_type_abbrev": "GBM",
        "grade": "4",
        "stage": "NA",
        "genomic_alteration": "unknown",
        "lesion_type": "primary"
    },
    "GSE131928.MGHBT1187": {
        "pub_url": "https://pubmed.ncbi.nlm.nih.gov/31327527/",
        "pub_name": "Neftel et al. (2019)",
        "age": "13",
        "sex": "male",
        "cancer_type": "glioblastoma",
        "cancer_type_abbrev": "GBM",
        "grade": "4",
        "stage": "NA",
        "genomic_alteration": "unknown",
        "lesion_type": "recurrence"
    },
    "GSE131928.MGHBT786": {
        "pub_url": "https://pubmed.ncbi.nlm.nih.gov/31327527/",
        "pub_name": "Neftel et al. (2019)",
        "age": "13",
        "sex": "male",
        "cancer_type": "glioblastoma",
        "cancer_type_abbrev": "GBM",
        "grade": "4",
        "stage": "NA",
        "genomic_alteration": "unknown",
        "lesion_type": "recurrence"
    },
    "GSE131928.MGHBT920": {
        "pub_url": "https://pubmed.ncbi.nlm.nih.gov/31327527/",
        "pub_name": "Neftel et al. (2019)",
        "age": "6 weeks",
        "sex": "male",
        "cancer_type": "glioblastoma",
        "cancer_type_abbrev": "GBM",
        "grade": "4",
        "stage": "NA",
        "genomic_alteration": "unknown",
        "lesion_type": "primary"
    },
    "GSE131928.MGH66": {
        "pub_url": "https://pubmed.ncbi.nlm.nih.gov/31327527/",
        "pub_name": "Neftel et al. (2019)",
        "age": "67",
        "sex": "male",
        "cancer_type": "glioblastoma",
        "cancer_type_abbrev": "GBM",
        "grade": "4",
        "stage": "NA",
        "genomic_alteration": "EGFR positive, MGMT methylated",
        "lesion_type": "primary"
    },
    "GSE131928.MGH105": {
        "pub_url": "https://pubmed.ncbi.nlm.nih.gov/31327527/",
        "pub_name": "Neftel et al. (2019)",
        "age": "67",
        "sex": "female",
        "cancer_type": "glioblastoma",
        "cancer_type_abbrev": "GBM",
        "grade": "4",
        "stage": "NA",
        "genomic_alteration": "EGFR positive, MGMT methylated",
        "lesion_type": "primary"
    },
    "GSE131928.MGH104": {
        "pub_url": "https://pubmed.ncbi.nlm.nih.gov/31327527/",
        "pub_name": "Neftel et al. (2019)",
        "age": "65",
        "sex": "female",
        "cancer_type": "glioblastoma",
        "cancer_type_abbrev": "GBM",
        "grade": "4",
        "stage": "NA",
        "genomic_alteration": "EGFR positive, MGMT non-methylated",
        "lesion_type": "primary"
    },
    "GSE131928.MGH106": {
        "pub_url": "https://pubmed.ncbi.nlm.nih.gov/31327527/",
        "pub_name": "Neftel et al. (2019)",
        "age": "66",
        "sex": "male",
        "cancer_type": "glioblastoma",
        "cancer_type_abbrev": "GBM",
        "grade": "4",
        "stage": "NA",
        "genomic_alteration": "EGFR positive, MGMT non-methylated",
        "lesion_type": "primary"
    },
    "GSE70630.MGH102.10x": {
        "pub_url": "https://pubmed.ncbi.nlm.nih.gov/31327527/",
        "pub_name": "Neftel et al. (2019)",
        "age": "65",
        "sex": "male",
        "cancer_type": "glioblastoma",
        "cancer_type_abbrev": "GBM",
        "grade": "4",
        "stage": "NA",
        "genomic_alteration": "MGMT non-methylated",
        "lesion_type": "primary"
    },
    "GSE70630.MGH105.10x": {
        "pub_url": "https://pubmed.ncbi.nlm.nih.gov/31327527/",
        "pub_name": "Neftel et al. (2019)",
        "age": "67",
        "sex": "female",
        "cancer_type": "glioblastoma",
        "cancer_type_abbrev": "GBM",
        "grade": "4",
        "stage": "NA",
        "genomic_alteration": "EGFR positive, MGMT methylated",
        "lesion_type": "primary"
    },
    "GSE70630.MGH115.10x": {
        "pub_url": "https://pubmed.ncbi.nlm.nih.gov/31327527/",
        "pub_name": "Neftel et al. (2019)",
        "age": "69",
        "sex": "female",
        "cancer_type": "glioblastoma",
        "cancer_type_abbrev": "GBM",
        "grade": "4",
        "stage": "NA",
        "genomic_alteration": "EGFR positive, MGMT non-methylated",
        "lesion_type": "primary"
    },
    "GSE70630.MGHBT1187.10x": {
        "pub_url": "https://pubmed.ncbi.nlm.nih.gov/31327527/",
        "pub_name": "Neftel et al. (2019)",
        "age": "13",
        "sex": "male",
        "cancer_type": "glioblastoma",
        "cancer_type_abbrev": "GBM",
        "grade": "4",
        "stage": "NA",
        "genomic_alteration": "unknown",
        "lesion_type": "recurrence"
    },
    "GSE70630.MGH124.10x": {
        "pub_url": "https://pubmed.ncbi.nlm.nih.gov/31327527/",
        "pub_name": "Neftel et al. (2019)",
        "age": "68",
        "sex": "female",
        "cancer_type": "glioblastoma",
        "cancer_type_abbrev": "GBM",
        "grade": "4",
        "stage": "NA",
        "genomic_alteration": "MGMT non-methylated",
        "lesion_type": "primary"
    },
    "GSE70630.MGH125.10x": {
        "pub_url": "https://pubmed.ncbi.nlm.nih.gov/31327527/",
        "pub_name": "Neftel et al. (2019)",
        "age": "76",
        "sex": "male",
        "cancer_type": "glioblastoma",
        "cancer_type_abbrev": "GBM",
        "grade": "4",
        "stage": "NA",
        "genomic_alteration": "MGMT non-methylated",
        "lesion_type": "primary"
    },
    "GSE70630.MGH126.10x": {
        "pub_url": "https://pubmed.ncbi.nlm.nih.gov/31327527/",
        "pub_name": "Neftel et al. (2019)",
        "age": "65",
        "sex": "male",
        "cancer_type": "glioblastoma",
        "cancer_type_abbrev": "GBM",
        "grade": "4",
        "stage": "NA",
        "genomic_alteration": "MGMT methylated",
        "lesion_type": "primary"
    },
    "GSE144236.P1": {
        "pub_url": "https://www.ncbi.nlm.nih.gov/pmc/articles/PMC7391009/",
        "pub_name": "Ji et al. (2020)",
        "age": "83",
        "sex": "male",
        "cancer_type": "cutaneous squamous cell carcinoma",
        "cancer_type_abbrev": "CSCC",
        "grade": "unknown",
        "stage": "unknown",
        "genomic_alteration": "unknown",
        "lesion_type": "primary"
    },
    "GSE144236.P2": {
        "pub_url": "https://www.ncbi.nlm.nih.gov/pmc/articles/PMC7391009/",
        "pub_name": "Ji et al. (2020)",
        "age": "69",
        "sex": "male",
        "cancer_type": "cutaneous squamous cell carcinoma",
        "cancer_type_abbrev": "CSCC",
        "grade": "unknown",
        "stage": "unknown",
        "genomic_alteration": "unknown",
        "lesion_type": "primary"
    },
    "GSE144236.P3": {
        "pub_url": "https://www.ncbi.nlm.nih.gov/pmc/articles/PMC7391009/",
        "pub_name": "Ji et al. (2020)",
        "age": "71",
        "sex": "male",
        "cancer_type": "cutaneous squamous cell carcinoma",
        "cancer_type_abbrev": "CSCC",
        "grade": "unknown",
        "stage": "unknown",
        "genomic_alteration": "unknown",
        "lesion_type": "primary"
    },
    "GSE144236.P4": {
        "pub_url": "https://www.ncbi.nlm.nih.gov/pmc/articles/PMC7391009/",
        "pub_name": "Ji et al. (2020)",
        "age": "75",
        "sex": "female",
        "cancer_type": "cutaneous squamous cell carcinoma",
        "cancer_type_abbrev": "CSCC",
        "grade": "unknown",
        "stage": "unknown",
        "genomic_alteration": "unknown",
        "lesion_type": "primary"
    },
    "GSE144236.P5": {
        "pub_url": "https://www.ncbi.nlm.nih.gov/pmc/articles/PMC7391009/",
        "pub_name": "Ji et al. (2020)",
        "age": "98",
        "sex": "male",
        "cancer_type": "cutaneous squamous cell carcinoma",
        "cancer_type_abbrev": "CSCC",
        "grade": "unknown",
        "stage": "unknown",
        "genomic_alteration": "unknown",
        "lesion_type": "primary"
    },
    "GSE144236.P6": {
        "pub_url": "https://www.ncbi.nlm.nih.gov/pmc/articles/PMC7391009/",
        "pub_name": "Ji et al. (2020)",
        "age": "96",
        "sex": "female",
        "cancer_type": "cutaneous squamous cell carcinoma",
        "cancer_type_abbrev": "CSCC",
        "grade": "unknown",
        "stage": "unknown",
        "genomic_alteration": "unknown",
        "lesion_type": "primary"
    },
    "GSE144236.P7": {
        "pub_url": "https://www.ncbi.nlm.nih.gov/pmc/articles/PMC7391009/",
        "pub_name": "Ji et al. (2020)",
        "age": "75",
        "sex": "male",
        "cancer_type": "cutaneous squamous cell carcinoma",
        "cancer_type_abbrev": "CSCC",
        "grade": "unknown",
        "stage": "unknown",
        "genomic_alteration": "unknown",
        "lesion_type": "primary"
    },
    "GSE144236.P8": {
        "pub_url": "https://www.ncbi.nlm.nih.gov/pmc/articles/PMC7391009/",
        "pub_name": "Ji et al. (2020)",
        "age": "63",
        "sex": "male",
        "cancer_type": "cutaneous squamous cell carcinoma",
        "cancer_type_abbrev": "CSCC",
        "grade": "uknown",
        "stage": "unknown",
        "genomic_alteration": "unknown",
        "lesion_type": "primary"
    },
    "GSE144236.P9": {
        "pub_url": "https://www.ncbi.nlm.nih.gov/pmc/articles/PMC7391009/",
        "pub_name": "Ji et al. (2020)",
        "age": "87",
        "sex": "male",
        "cancer_type": "cutaneous squamous cell carcinoma",
        "cancer_type_abbrev": "CSCC",
        "grade": "unknown",
        "stage": "unknown",
        "genomic_alteration": "unknown",
        "lesion_type": "primary"
    },
    "GSE144236.P10": {
        "pub_url": "https://www.ncbi.nlm.nih.gov/pmc/articles/PMC7391009/",
        "pub_name": "Ji et al. (2020)",
        "age": "71",
        "sex": "male",
        "cancer_type": "cutaneous squamous cell carcinoma",
        "cancer_type_abbrev": "CSCC",
        "grade": "unknown",
        "stage": "unknown",
        "genomic_alteration": "uknown",
        "lesion_type": "recurrent"
    },
    "GSE102130.MUV1": {
        "pub_url": "https://pubmed.ncbi.nlm.nih.gov/29674595/",
        "pub_name": "Filbin et al. (2018)",
        "age": "4",
        "sex": "female",
        "cancer_type": "glioma with histone H3 lysine27-to-methionine mutations",
        "cancer_type_abbrev": "HGG",
        "grade": "unknown",
        "stage": "unknown",
        "genomic_alteration": "K27M mutation: H3F3A",
        "lesion_type": "primary"
    },
    "GSE102130.MUV5": {
        "pub_url": "https://pubmed.ncbi.nlm.nih.gov/29674595/",
        "pub_name": "Filbin et al. (2018)",
        "age": "2.5",
        "sex": "male",
        "cancer_type": "glioma with histone H3 lysine27-to-methionine mutations",
        "cancer_type_abbrev": "HGG",
        "grade": "unknown",
        "stage": "unknown",
        "genomic_alteration": "K27M mutation: HIST1H3B",
        "lesion_type": "primary"
    },
    "GSE102130.MUV10": {
        "pub_url": "https://pubmed.ncbi.nlm.nih.gov/29674595/",
        "pub_name": "Filbin et al. (2018)",
        "age": "9",
        "sex": "female",
        "cancer_type": "glioma with histone H3 lysine27-to-methionine mutations",
        "cancer_type_abbrev": "HGG",
        "grade": "unknown",
        "stage": "unknown",
        "genomic_alteration": "K27M mutation: H3F3A",
        "lesion_type": "primary"
    },
    "GSE102130.BCH836": {
        "pub_url": "https://pubmed.ncbi.nlm.nih.gov/29674595/",
        "pub_name": "Filbin et al. (2018)",
        "age": "5",
        "sex": "female",
        "cancer_type": "glioma with histone H3 lysine27-to-methionine mutations",
        "cancer_type_abbrev": "HGG",
        "grade": "unknown",
        "stage": "unknown",
        "genomic_alteration": "K27M mutation: H3F3A",
        "lesion_type": "primary"
    },
    "GSE102130.BCH869": {
        "pub_url": "https://pubmed.ncbi.nlm.nih.gov/29674595/",
        "pub_name": "Filbin et al. (2018)",
        "age": "7",
        "sex": "female",
        "cancer_type": "glioma with histone H3 lysine27-to-methionine mutations",
        "cancer_type_abbrev": "HGG",
        "grade": "unknown",
        "stage": "unknown",
        "genomic_alteration": "K27M mutation: H3F3A",
        "lesion_type": "primary"
    },
    "GSE102130.BCH1126": {
        "pub_url": "https://pubmed.ncbi.nlm.nih.gov/29674595/",
        "pub_name": "Filbin et al. (2018)",
        "age": "10",
        "sex": "female",
        "cancer_type": "glioma with histone H3 lysine27-to-methionine mutations",
        "cancer_type_abbrev": "HGG",
        "grade": "unknown",
        "stage": "unknown",
        "genomic_alteration": "K27M mutation: H3F3A",
        "lesion_type": "primary"
    },
    "GSE89567.MGH42": {
        "pub_url": "https://pubmed.ncbi.nlm.nih.gov/28360267/",
        "pub_name": "Venteicher et al. (2017)",
        "age": "47",
        "sex": "female",
        "cancer_type": "anaplastic astrocytoma",
        "cancer_type_abbrev": "HGG",
        "grade": "3",
        "stage": "unknown",
        "genomic_alteration": "IDH1 mutation: R132H, P53 mutation: R273C, APC mutation: S966G",
        "lesion_type": "primary"
    },
    "GSE89567.MGH61": {
        "pub_url": "https://pubmed.ncbi.nlm.nih.gov/28360267/",
        "pub_name": "Venteicher et al. (2017)",
        "age": "24",
        "sex": "male",
        "cancer_type": "anaplastic astrocytoma",
        "cancer_type_abbrev": "HGG",
        "grade": "3",
        "stage": "unknown",
        "genomic_alteration": "IDH1 mutation: R132H",
        "lesion_type": "primary"
    },
    "GSE89567.MGH43": {
        "pub_url": "https://pubmed.ncbi.nlm.nih.gov/28360267/",
        "pub_name": "Venteicher et al. (2017)",
        "age": "45",
        "sex": "male",
        "cancer_type": "anaplastic astrocytoma",
        "cancer_type_abbrev": "HGG",
        "grade": "3",
        "stage": "unknown",
        "genomic_alteration": "IDH1 mutation: R132H, P53 mutation: V157F",
        "lesion_type": "recurrent"
    },
    "GSE89567.MGH45": {
        "pub_url": "https://pubmed.ncbi.nlm.nih.gov/28360267/",
        "pub_name": "Venteicher et al. (2017)",
        "age": "32",
        "sex": "female",
        "cancer_type": "glioblastoma",
        "cancer_type_abbrev": "GBM",
        "grade": "4",
        "stage": "unknown",
        "genomic_alteration": "IDH1 mutation: R132H",
        "lesion_type": "recurrent"
    },
    "GSE89567.MGH44": {
        "pub_url": "https://pubmed.ncbi.nlm.nih.gov/28360267/",
        "pub_name": "Venteicher et al. (2017)",
        "age": "32",
        "sex": "male",
        "cancer_type": "anaplastic astrocytoma",
        "cancer_type_abbrev": "HGG",
        "grade": "3",
        "stage": "unknown",
        "genomic_alteration": "IDH1 mutation: R132H",
        "lesion_type": "primary"
    },
    "GSE89567.MGH56": {
        "pub_url": "https://pubmed.ncbi.nlm.nih.gov/28360267/",
        "pub_name": "Venteicher et al. (2017)",
        "age": "male",
        "sex": "31",
        "cancer_type": "anaplastic astrocytoma",
        "cancer_type_abbrev": "HGG",
        "grade": "3",
        "stage": "unknown",
        "genomic_alteration": "IDH1 mutation: R132H",
        "lesion_type": "primary"
    },
    "GSE89567.MGH64": {
        "pub_url": "https://pubmed.ncbi.nlm.nih.gov/28360267/",
        "pub_name": "Venteicher et al. (2017)",
        "age": "40",
        "sex": "female",
        "cancer_type": "anaplastic astrocytoma",
        "cancer_type_abbrev": "HGG",
        "grade": "3",
        "stage": "unknown",
        "genomic_alteration": "IDH1 mutation: R132H, P53 mutation: R213X and R306X, PIK3CA mutation: R88Q",
        "lesion_type": "primary"
    },
    "GSE89567.MGH57": {
        "pub_url": "https://pubmed.ncbi.nlm.nih.gov/28360267/",
        "pub_name": "Venteicher et al. (2017)",
        "age": "42",
        "sex": "male",
        "cancer_type": "glioblastoma",
        "cancer_type_abbrev": "GBM",
        "grade": "4",
        "stage": "unknown",
        "genomic_alteration": "IDH1 mutation: R132C",
        "lesion_type": "primary"
    },
    "GSE89567.MGH103": {
        "pub_url": "https://pubmed.ncbi.nlm.nih.gov/28360267/",
        "pub_name": "Venteicher et al. (2017)",
        "age": "26",
        "sex": "female",
        "cancer_type": "anaplastic astrocytoma",
        "cancer_type_abbrev": "HGG",
        "grade": "3",
        "stage": "unknown",
        "genomic_alteration": "IDH1 mutation: R132H, P53 mutation: C299R",
        "lesion_type": "primary"
    },
    "GSE89567.MGH107": {
        "pub_url": "https://pubmed.ncbi.nlm.nih.gov/28360267/",
        "pub_name": "Venteicher et al. (2017)",
        "age": "47",
        "sex": "female",
        "cancer_type": "diffuse astrocytoma",
        "cancer_type_abbrev": "LGG",
        "grade": "2",
        "stage": "unknown",
        "genomic_alteration": "IDH1 mutation: R132H, P53 mutation: T582M, ATRX mutation: F2113 frameshift, BRCA1 mutation: T582M",
        "lesion_type": "primary"
    },
    "GSE75688.BC02": {
        "pub_url": "https://pubmed.ncbi.nlm.nih.gov/28474673/",
        "pub_name": "Chung et al. (2017)",
        "age": "72",
        "sex": "female",
        "cancer_type": "breast cancer",
        "cancer_type_abbrev": "BRCA",
        "grade": "unknown",
        "stage": "3A",
        "genomic_alteration": "ER: positive, PR: positive, HER2: 2+/3",
        "lesion_type": "primary"
    },
    "GSE75688.BC03LN": {
        "pub_url": "https://pubmed.ncbi.nlm.nih.gov/28474673/",
        "pub_name": "Chung et al. (2017)",
        "age": "72",
        "sex": "female",
        "cancer_type": "breast cancer",
        "cancer_type_abbrev": "BRCA",
        "grade": "unknown",
        "stage": "2B",
        "genomic_alteration": "ER: positive, PR: positive, HER2: 3+/3",
        "lesion_type": "metastasis"
    },
    "GSE75688.BC04": {
        "pub_url": "https://pubmed.ncbi.nlm.nih.gov/28474673/",
        "pub_name": "Chung et al. (2017)",
        "age": "67",
        "sex": "female",
        "cancer_type": "breast cancer",
        "cancer_type_abbrev": "BRCA",
        "grade": "unknown",
        "stage": "2A",
        "genomic_alteration": "ER: negative, PR: negative, HER2: 3+/3",
        "lesion_type": "primary"
    },
    "GSE75688.BC05": {
        "pub_url": "https://pubmed.ncbi.nlm.nih.gov/28474673/",
        "pub_name": "Chung et al. (2017)",
        "age": "46",
        "sex": "female",
        "cancer_type": "breast cancer",
        "cancer_type_abbrev": "BRCA",
        "grade": "unknown",
        "stage": "1B",
        "genomic_alteration": "ER: negative, PR: negative, HER2: 3+/3",
        "lesion_type": "primary"
    },
    "GSE75688.BC07": {
        "pub_url": "https://pubmed.ncbi.nlm.nih.gov/28474673/",
        "pub_name": "Chung et al. (2017)",
        "age": "71",
        "sex": "female",
        "cancer_type": "breast cancer",
        "cancer_type_abbrev": "BRCA",
        "grade": "unknown",
        "stage": "3C",
        "genomic_alteration": "ER: negative, PR: negative, HER2: 1+/3",
        "lesion_type": "primary"
    },
    "GSE75688.BC09": {
        "pub_url": "https://pubmed.ncbi.nlm.nih.gov/28474673/",
        "pub_name": "Chung et al. (2017)",
        "age": "53",
        "sex": "female",
        "cancer_type": "breast cancer",
        "cancer_type_abbrev": "BRCA",
        "grade": "unknown",
        "stage": "2A",
        "genomic_alteration": "ER: negative, PR: negative, HER2: 1+/3",
        "lesion_type": "primary"
    },
    "GSE139829.UMM041L": {
        "pub_url": "https://pubmed.ncbi.nlm.nih.gov/31980621/",
        "pub_name": "Durante et al. (2020)",
        "age": "63",
        "sex": "female",
        "cancer_type": "uveal melanoma",
        "cancer_type_abbrev": "UM",
        "grade": "unknown",
        "stage": "unknown",
        "genomic_alteration": "GNAQ mutation, BAP1 mutation",
        "lesion_type": "metastasis"
    },
    "GSE139829.UMM069": {
        "pub_url": "https://pubmed.ncbi.nlm.nih.gov/31980621/",
        "pub_name": "Durante et al. (2020)",
        "age": "80",
        "sex": "female",
        "cancer_type": "uveal melanoma",
        "cancer_type_abbrev": "UM",
        "grade": "unknown",
        "stage": "unknown",
        "genomic_alteration": "GNAQ mutation, BAP1 mutation",
        "lesion_type": "primary"
    },
    "GSE139829.UMM064": {
        "pub_url": "https://pubmed.ncbi.nlm.nih.gov/31980621/",
        "pub_name": "Durante et al. (2020)",
        "age": "77",
        "sex": "male",
        "cancer_type": "uveal melanoma",
        "cancer_type_abbrev": "UM",
        "grade": "unknown",
        "stage": "unknown",
        "genomic_alteration": "GNAQ mutation, BAP1 mutation",
        "lesion_type": "primary"
    },
    "GSE139829.UMM067L": {
        "pub_url": "https://pubmed.ncbi.nlm.nih.gov/31980621/",
        "pub_name": "Durante et al. (2020)",
        "age": "73",
        "sex": "male",
        "cancer_type": "uveal melanoma",
        "cancer_type_abbrev": "UM",
        "grade": "unknown",
        "stage": "unknown",
        "genomic_alteration": "GNA11 mutation, BAP1 mutation",
        "lesion_type": "metastasis"
    },
    "GSE139829.UMM059": {
        "pub_url": "https://pubmed.ncbi.nlm.nih.gov/31980621/",
        "pub_name": "Durante et al. (2020)",
        "age": "86",
        "sex": "female",
        "cancer_type": "uveal melanoma",
        "cancer_type_abbrev": "UM",
        "grade": "unknown",
        "stage": "unknown",
        "genomic_alteration": "GNA11 mutation, BAP1 mutation",
        "lesion_type": "primary"
    },
    "GSE139829.UMM063": {
        "pub_url": "https://pubmed.ncbi.nlm.nih.gov/31980621/",
        "pub_name": "Durante et al. (2020)",
        "age": "66",
        "sex": "male",
        "cancer_type": "uveal melanoma",
        "cancer_type_abbrev": "UM",
        "grade": "unknown",
        "stage": "unknown",
        "genomic_alteration": "GNAQ mutation, BAP1 mutation",
        "lesion_type": "primary"
    },
    "GSE139829.UMM066": {
        "pub_url": "https://pubmed.ncbi.nlm.nih.gov/31980621/",
        "pub_name": "Durante et al. (2020)",
        "age": "53",
        "sex": "male",
        "cancer_type": "uveal melanoma",
        "cancer_type_abbrev": "UM",
        "grade": "unknown",
        "stage": "unknown",
        "genomic_alteration": "GNAQ mutation, BAP1 mutation",
        "lesion_type": "primary"
    },
    "GSE139829.UMM061": {
        "pub_url": "https://pubmed.ncbi.nlm.nih.gov/31980621/",
        "pub_name": "Durante et al. (2020)",
        "age": "71",
        "sex": "female",
        "cancer_type": "uveal melanoma",
        "cancer_type_abbrev": "UM",
        "grade": "unknown",
        "stage": "unknown",
        "genomic_alteration": "GNA11 mutation, BAP1 mutation",
        "lesion_type": "primary"
    },
    "GSE139829.UMM062": {
        "pub_url": "https://pubmed.ncbi.nlm.nih.gov/31980621/",
        "pub_name": "Durante et al. (2020)",
        "age": "69",
        "sex": "male",
        "cancer_type": "uveal melanoma",
        "cancer_type_abbrev": "UM",
        "grade": "unkown",
        "stage": "unkown",
        "genomic_alteration": "GNAQ mutation, EIF1AX mutation",
        "lesion_type": "primary"
    },
    "GSE139829.UMM065": {
        "pub_url": "https://pubmed.ncbi.nlm.nih.gov/31980621/",
        "pub_name": "Durante et al. (2020)",
        "age": "44",
        "sex": "female",
        "cancer_type": "uveal melanoma",
        "cancer_type_abbrev": "UM",
        "grade": "unknown",
        "stage": "unknown",
        "genomic_alteration": "GNA11 mutation, EIF1AX mutation",
        "lesion_type": "primary"
    },
    "GSE139829.BSSR0022": {
        "pub_url": "https://pubmed.ncbi.nlm.nih.gov/31980621/",
        "pub_name": "Durante et al. (2020)",
        "age": "68",
        "sex": "female",
        "cancer_type": "uveal melanoma",
        "cancer_type_abbrev": "UM",
        "grade": "unknown",
        "stage": "unknown",
        "genomic_alteration": "GNAQ mutation, SF3B1 mutation",
        "lesion_type": "metastasis"
    },
    "GSE134520.EGC": {
        "pub_url": "https://pubmed.ncbi.nlm.nih.gov/31067475/",
        "pub_name": "Zhang et al. (2019)",
        "age": "67",
        "sex": "male",
        "cancer_type": "stomach cancer",
        "cancer_type_abbrev": "STAD",
        "grade": "unknown",
        "stage": "unknown",
        "genomic_alteration": "unknown",
        "lesion_type": "primary"
    },
    "GSE140312.primary": {
        "pub_url": "https://pubmed.ncbi.nlm.nih.gov/32054662/",
        "pub_name": "Rao et al. (2020)",
        "age": "58",
        "sex": "female",
        "cancer_type": "small intestinal neuroendocrine cancer",
        "cancer_type_abbrev": "GINET",
        "grade": "unknown",
        "stage": "unknown",
        "genomic_alteration": "unknown",
        "lesion_type": "primary"
    },
    "GSE140312.metastasis": {
        "pub_url": "https://pubmed.ncbi.nlm.nih.gov/32054662/",
        "pub_name": "Rao et al. (2020)",
        "age": "58",
        "sex": "female",
        "cancer_type": "small intestinal neuroendocrine cancer",
        "cancer_type_abbrev": "GINET",
        "grade": "unknown",
        "stage": "unknown",
        "genomic_alteration": "unknown",
        "lesion_type": "metastasis"
    }
}
